util4all/__init__.py
util4all/core.py
util4all/main.py
util4all/utils.py
util4all/cli/__init__.py
util4all/cli/log_utils.py
util4all/cli/logging.py
util4all-0.1.1.dist-info/METADATA
util4all-0.1.1.dist-info/WHEEL
util4all-0.1.1.dist-info/entry_points.txt
util4all-0.1.1.dist-info/top_level.txt
util4all-0.1.1.dist-info/RECORD
